auth_server_client
