Metadata-Version: 1.0
Name: AuthServerClient
Version: 0.0.3
Summary: AuthServer client lib
Home-page: https://github.com/AF83/auth_server_client_py
Author: Pierre Ruyssen (AF83)
Author-email: pierre@ruyssen.eu
License: AGPL v3
Keywords: authserver oauth2 authentication authorization wsgi middleware
Platform: UNKNOWN
Classifier: Development Status :: 3 - Alpha
Classifier: Intended Audience :: Developers
Classifier: License :: OSI Approved :: GNU Affero General Public License v3
Classifier: Programming Language :: Python
Classifier: Topic :: Internet :: WWW/HTTP :: WSGI
Classifier: Topic :: Software Development :: Libraries :: Python Modules
